pgcom/__init__.py
pgcom/base.py
pgcom/commuter.py
pgcom/connector.py
pgcom/exc.py
pgcom/listener.py
pgcom/queries.py
pgcom/version.py
pgcom-0.2.2.dist-info/LICENSE
pgcom-0.2.2.dist-info/METADATA
pgcom-0.2.2.dist-info/WHEEL
pgcom-0.2.2.dist-info/top_level.txt
pgcom-0.2.2.dist-info/RECORD
