Metadata-Version: 2.1
Name: pgcom
Version: 0.2.2
Summary: PostgreSQL communication manager
Home-page: https://github.com/viktorsapozhok/pgcom
Author: Alex Piskun
Author-email: piskun.aleksey@gmail.com
License: UNKNOWN
Platform: UNKNOWN
Requires-Python: >=3.6
Requires-Dist: pandas (>=0.24.0)
Requires-Dist: psycopg2-binary (>=2.7.7)
Provides-Extra: docs
Requires-Dist: sphinx ; extra == 'docs'
Requires-Dist: sphinx-rtd-theme ; extra == 'docs'
Requires-Dist: sphinx-autodoc-typehints ; extra == 'docs'
Provides-Extra: test
Requires-Dist: pytest ; extra == 'test'
Requires-Dist: tox ; extra == 'test'
